video/__init__.py
video/video.py
CV_video-0.1.2.dist-info/LICENSE
CV_video-0.1.2.dist-info/METADATA
CV_video-0.1.2.dist-info/WHEEL
CV_video-0.1.2.dist-info/top_level.txt
CV_video-0.1.2.dist-info/zip-safe
CV_video-0.1.2.dist-info/RECORD
